[{"1": {"this": 0.0, "species": 1.0, "is": 0.0, "endemic": 0.0, "to": 0.0, "brazil": 0.0, ".": 0.0}, "2": {"this species": 0.5, "species is": 0.5, "is endemic": 0.0, "endemic to": 0.0, "to brazil": 0.0, "brazil .": 0.0}, "3": {"this species is": 0.3333333333333333, "species is endemic": 0.3333333333333333, "is endemic to": 0.0, "endemic to brazil": 0.0, "to brazil .": 0.0}, "4": {"this species is endemic": 0.25, "species is endemic to": 0.25, "is endemic to brazil": 0.0, "endemic to brazil .": 0.0}}, {"1": {"heyward": 1.0, "won": 0.0, "in": 0.0, "the": 0.0, "runoff": 0.0, "election": 0.0, "against": 0.0, "w.": 0.0, "jasper": 0.0, "talbert": 0.0, "and": 0.0, "became": 0.0, "88th": 0.0, "governor": 1.0, "of": 1.0, "south": 1.0, "carolina": 1.0, "after": 0.0, "running": 0.0, "unopposed": 0.0, "general": 0.0, ".": 0.0}, "2": {"heyward won": 0.5, "won in": 0.0, "in the": 0.0, "the runoff": 0.0, "runoff election": 0.0, "election against": 0.0, "against w.": 0.0, "w. jasper": 0.0, "jasper talbert": 0.0, "talbert and": 0.0, "and became": 0.0, "became the": 0.0, "the 88th": 0.0, "88th governor": 0.5, "governor of": 1.0, "of south": 1.0, "south carolina": 1.0, "carolina after": 0.5, "after running": 0.0, "running unopposed": 0.0, "unopposed in": 0.0, "the general": 0.0, "general election": 0.0, "election .": 0.0}, "3": {"heyward won in": 0.3333333333333333, "won in the": 0.0, "in the runoff": 0.0, "the runoff election": 0.0, "runoff election against": 0.0, "election against w.": 0.0, "against w. jasper": 0.0, "w. jasper talbert": 0.0, "jasper talbert and": 0.0, "talbert and became": 0.0, "and became the": 0.0, "became the 88th": 0.0, "the 88th governor": 0.3333333333333333, "88th governor of": 0.6666666666666666, "governor of south": 1.0, "of south carolina": 1.0, "south carolina after": 0.6666666666666666, "carolina after running": 0.3333333333333333, "after running unopposed": 0.0, "running unopposed in": 0.0, "unopposed in the": 0.0, "in the general": 0.0, "the general election": 0.0, "general election .": 0.0}, "4": {"heyward won in the": 0.25, "won in the runoff": 0.0, "in the runoff election": 0.0, "the runoff election against": 0.0, "runoff election against w.": 0.0, "election against w. jasper": 0.0, "against w. jasper talbert": 0.0, "w. jasper talbert and": 0.0, "jasper talbert and became": 0.0, "talbert and became the": 0.0, "and became the 88th": 0.0, "became the 88th governor": 0.25, "the 88th governor of": 0.5, "88th governor of south": 0.75, "governor of south carolina": 1.0, "of south carolina after": 0.75, "south carolina after running": 0.5, "carolina after running unopposed": 0.25, "after running unopposed in": 0.0, "running unopposed in the": 0.0, "unopposed in the general": 0.0, "in the general election": 0.0, "the general election .": 0.0}}]